["{\"n\": 1, \"episode_reward_min\": -21.0, \"episode_reward_mean\": -21.0, \"episode_reward_max\": -21.0, \"episode_len_mean\": 1026.0, \"learn_time_ms\": 1001013.478}", "{\"n\": 2, \"episode_reward_min\": -21.0, \"episode_reward_mean\": -21.0, \"episode_reward_max\": -21.0, \"episode_len_mean\": 1015.1666666666666, \"learn_time_ms\": 1000540.6}", "{\"n\": 3, \"episode_reward_min\": -21.0, \"episode_reward_mean\": -21.0, \"episode_reward_max\": -21.0, \"episode_len_mean\": 1016.7, \"learn_time_ms\": 1000105.831}", "{\"n\": 4, \"episode_reward_min\": -21.0, \"episode_reward_mean\": -21.0, \"episode_reward_max\": -21.0, \"episode_len_mean\": 1017.0, \"learn_time_ms\": 999862.597}", "{\"n\": 5, \"episode_reward_min\": -21.0, \"episode_reward_mean\": -21.0, \"episode_reward_max\": -21.0, \"episode_len_mean\": 1017.7647058823529, \"learn_time_ms\": 999446.627}", "{\"n\": 6, \"episode_reward_min\": -21.0, \"episode_reward_mean\": -21.0, \"episode_reward_max\": -21.0, \"episode_len_mean\": 1018.7, \"learn_time_ms\": 999164.75}", "{\"n\": 7, \"episode_reward_min\": -21.0, \"episode_reward_mean\": -20.958333333333332, \"episode_reward_max\": -20.0, \"episode_len_mean\": 1024.9583333333333, \"learn_time_ms\": 999133.758}", "{\"n\": 8, \"episode_reward_min\": -21.0, \"episode_reward_mean\": -20.964285714285715, \"episode_reward_max\": -20.0, \"episode_len_mean\": 1024.2142857142858, \"learn_time_ms\": 999206.765}", "{\"n\": 9, \"episode_reward_min\": -21.0, \"episode_reward_mean\": -20.96875, \"episode_reward_max\": -20.0, \"episode_len_mean\": 1026.0, \"learn_time_ms\": 999244.337}", "{\"n\": 10, \"episode_reward_min\": -21.0, \"episode_reward_mean\": -20.97222222222222, \"episode_reward_max\": -20.0, \"episode_len_mean\": 1027.8055555555557, \"learn_time_ms\": 999328.764}", "{\"n\": 11, \"episode_reward_min\": -21.0, \"episode_reward_mean\": -20.975, \"episode_reward_max\": -20.0, \"episode_len_mean\": 1026.575, \"learn_time_ms\": 999264.749}", "{\"n\": 12, \"episode_reward_min\": -21.0, \"episode_reward_mean\": -20.977272727272727, \"episode_reward_max\": -20.0, \"episode_len_mean\": 1026.5, \"learn_time_ms\": 999405.851}", "{\"n\": 13, \"episode_reward_min\": -21.0, \"episode_reward_mean\": -20.979166666666668, \"episode_reward_max\": -20.0, \"episode_len_mean\": 1027.7083333333333, \"learn_time_ms\": 999518.994}", "{\"n\": 14, \"episode_reward_min\": -21.0, \"episode_reward_mean\": -20.98076923076923, \"episode_reward_max\": -20.0, \"episode_len_mean\": 1026.4615384615386, \"learn_time_ms\": 999661.026}", "{\"n\": 15, \"episode_reward_min\": -21.0, \"episode_reward_mean\": -20.964285714285715, \"episode_reward_max\": -20.0, \"episode_len_mean\": 1027.4464285714287, \"learn_time_ms\": 999870.592}", "{\"n\": 16, \"episode_reward_min\": -21.0, \"episode_reward_mean\": -20.95, \"episode_reward_max\": -20.0, \"episode_len_mean\": 1031.3, \"learn_time_ms\": 1000126.565}", "{\"n\": 17, \"episode_reward_min\": -21.0, \"episode_reward_mean\": -20.953125, \"episode_reward_max\": -20.0, \"episode_len_mean\": 1031.234375, \"learn_time_ms\": 1000291.922}", "{\"n\": 18, \"episode_reward_min\": -21.0, \"episode_reward_mean\": -20.941176470588236, \"episode_reward_max\": -20.0, \"episode_len_mean\": 1033.1176470588234, \"learn_time_ms\": 1000291.812}", "{\"n\": 19, \"episode_reward_min\": -21.0, \"episode_reward_mean\": -20.944444444444443, \"episode_reward_max\": -20.0, \"episode_len_mean\": 1032.2916666666667, \"learn_time_ms\": 1000329.635}", "{\"n\": 20, \"episode_reward_min\": -21.0, \"episode_reward_mean\": -20.92105263157895, \"episode_reward_max\": -20.0, \"episode_len_mean\": 1034.6842105263158, \"learn_time_ms\": 1000240.741}", "{\"n\": 21, \"episode_reward_min\": -21.0, \"episode_reward_mean\": -20.9125, \"episode_reward_max\": -20.0, \"episode_len_mean\": 1035.075, \"learn_time_ms\": 1000149.592}", "{\"n\": 22, \"episode_reward_min\": -21.0, \"episode_reward_mean\": -20.916666666666668, \"episode_reward_max\": -20.0, \"episode_len_mean\": 1036.047619047619, \"learn_time_ms\": 999999.164}", "{\"n\": 23, \"episode_reward_min\": -21.0, \"episode_reward_mean\": -20.90909090909091, \"episode_reward_max\": -20.0, \"episode_len_mean\": 1037.0568181818182, \"learn_time_ms\": 999953.343}", "{\"n\": 24, \"episode_reward_min\": -21.0, \"episode_reward_mean\": -20.91304347826087, \"episode_reward_max\": -20.0, \"episode_len_mean\": 1037.4673913043478, \"learn_time_ms\": 999890.075}", "{\"n\": 25, \"episode_reward_min\": -21.0, \"episode_reward_mean\": -20.916666666666668, \"episode_reward_max\": -20.0, \"episode_len_mean\": 1036.5729166666667, \"learn_time_ms\": 999880.219}", "{\"n\": 26, \"episode_reward_min\": -21.0, \"episode_reward_mean\": -20.91, \"episode_reward_max\": -20.0, \"episode_len_mean\": 1037.17, \"learn_time_ms\": 999831.912}", "{\"n\": 27, \"episode_reward_min\": -21.0, \"episode_reward_mean\": -20.91, \"episode_reward_max\": -20.0, \"episode_len_mean\": 1037.01, \"learn_time_ms\": 999801.482}", "{\"n\": 28, \"episode_reward_min\": -21.0, \"episode_reward_mean\": -20.9, \"episode_reward_max\": -20.0, \"episode_len_mean\": 1038.62, \"learn_time_ms\": 999926.037}", "{\"n\": 29, \"episode_reward_min\": -21.0, \"episode_reward_mean\": -20.9, \"episode_reward_max\": -20.0, \"episode_len_mean\": 1039.95, \"learn_time_ms\": 1000049.597}", "{\"n\": 30, \"episode_reward_min\": -21.0, \"episode_reward_mean\": -20.89, \"episode_reward_max\": -20.0, \"episode_len_mean\": 1041.71, \"learn_time_ms\": 1000150.944}", "{\"n\": 31, \"episode_reward_min\": -21.0, \"episode_reward_mean\": -20.87, \"episode_reward_max\": -20.0, \"episode_len_mean\": 1043.45, \"learn_time_ms\": 1000270.41}", "{\"n\": 32, \"episode_reward_min\": -21.0, \"episode_reward_mean\": -20.87, \"episode_reward_max\": -20.0, \"episode_len_mean\": 1043.27, \"learn_time_ms\": 1000371.043}", "{\"n\": 33, \"episode_reward_min\": -21.0, \"episode_reward_mean\": -20.86, \"episode_reward_max\": -20.0, \"episode_len_mean\": 1044.27, \"learn_time_ms\": 1000244.621}", "{\"n\": 34, \"episode_reward_min\": -21.0, \"episode_reward_mean\": -20.84, \"episode_reward_max\": -20.0, \"episode_len_mean\": 1046.49, \"learn_time_ms\": 1000191.922}", "{\"n\": 35, \"episode_reward_min\": -21.0, \"episode_reward_mean\": -20.83, \"episode_reward_max\": -20.0, \"episode_len_mean\": 1046.91, \"learn_time_ms\": 1000174.989}", "{\"n\": 36, \"episode_reward_min\": -21.0, \"episode_reward_mean\": -20.82, \"episode_reward_max\": -20.0, \"episode_len_mean\": 1049.82, \"learn_time_ms\": 1000134.837}", "{\"n\": 37, \"episode_reward_min\": -21.0, \"episode_reward_mean\": -20.81, \"episode_reward_max\": -20.0, \"episode_len_mean\": 1051.57, \"learn_time_ms\": 1000000.745}", "{\"n\": 38, \"episode_reward_min\": -21.0, \"episode_reward_mean\": -20.77, \"episode_reward_max\": -20.0, \"episode_len_mean\": 1055.25, \"learn_time_ms\": 999760.933}", "{\"n\": 39, \"episode_reward_min\": -21.0, \"episode_reward_mean\": -20.76, \"episode_reward_max\": -20.0, \"episode_len_mean\": 1055.48, \"learn_time_ms\": 999513.527}", "{\"n\": 40, \"episode_reward_min\": -21.0, \"episode_reward_mean\": -20.75, \"episode_reward_max\": -20.0, \"episode_len_mean\": 1058.06, \"learn_time_ms\": 999421.952}", "{\"n\": 41, \"episode_reward_min\": -21.0, \"episode_reward_mean\": -20.76, \"episode_reward_max\": -20.0, \"episode_len_mean\": 1058.82, \"learn_time_ms\": 999263.652}", "{\"n\": 42, \"episode_reward_min\": -21.0, \"episode_reward_mean\": -20.75, \"episode_reward_max\": -20.0, \"episode_len_mean\": 1058.27, \"learn_time_ms\": 999053.032}", "{\"n\": 43, \"episode_reward_min\": -21.0, \"episode_reward_mean\": -20.73, \"episode_reward_max\": -20.0, \"episode_len_mean\": 1061.24, \"learn_time_ms\": 999184.07}", "{\"n\": 44, \"episode_reward_min\": -21.0, \"episode_reward_mean\": -20.72, \"episode_reward_max\": -20.0, \"episode_len_mean\": 1062.56, \"learn_time_ms\": 999091.583}", "{\"n\": 45, \"episode_reward_min\": -21.0, \"episode_reward_mean\": -20.7, \"episode_reward_max\": -20.0, \"episode_len_mean\": 1064.46, \"learn_time_ms\": 999061.112}", "{\"n\": 46, \"episode_reward_min\": -21.0, \"episode_reward_mean\": -20.71, \"episode_reward_max\": -20.0, \"episode_len_mean\": 1063.45, \"learn_time_ms\": 999069.848}", "{\"n\": 47, \"episode_reward_min\": -21.0, \"episode_reward_mean\": -20.7, \"episode_reward_max\": -20.0, \"episode_len_mean\": 1066.01, \"learn_time_ms\": 999086.317}", "{\"n\": 48, \"episode_reward_min\": -21.0, \"episode_reward_mean\": -20.69, \"episode_reward_max\": -20.0, \"episode_len_mean\": 1067.24, \"learn_time_ms\": 999100.224}", "{\"n\": 49, \"episode_reward_min\": -21.0, \"episode_reward_mean\": -20.68, \"episode_reward_max\": -20.0, \"episode_len_mean\": 1066.95, \"learn_time_ms\": 999114.154}", "{\"n\": 50, \"episode_reward_min\": -21.0, \"episode_reward_mean\": -20.68, \"episode_reward_max\": -20.0, \"episode_len_mean\": 1068.2, \"learn_time_ms\": 999052.563}"]